<?xml version="1.0" encoding="utf-8"?>
<disqus xmlns="http://disqus.com" xmlns:dsq="http://disqus.com/disqus-internals"
        xmlns:xsi="http://www.w3.org/2001/XMLSchema-instance"
        >
    <category dsq:id="734737">
        <forum>sovietraregroove</forum>
        <title>General</title>
        <isDefault>true</isDefault>
    </category>
    <thread dsq:id="261687969">
        <id/>
        <forum>sovietraregroove</forum>
        <category dsq:id="734737"/>
        <link>http://localhost:8080/</link>
        <title>http://localhost:8080/</title>
        <message/>
        <createdAt>2011-03-24T03:49:34Z</createdAt>
        <author>
            <email>zeencd@gmail.com</email>
            <name>Pavel</name>
            <isAnonymous/>
            <username>zencd</username>
        </author>
        <ipAddress>188.134.44.209</ipAddress>
        <isClosed/>
        <isDeleted/>
    </thread>
    <thread dsq:id="261688000">
        <id/>
        <forum>sovietraregroove</forum>
        <category dsq:id="734737"/>
        <link>http://localhost:8080/11-blah-blah-blah.html</link>
        <title>http://localhost:8080/11-blah-blah-blah.html</title>
        <message/>
        <createdAt>2011-03-24T03:49:37Z</createdAt>
        <author>
            <email>zeencd@gmail.com</email>
            <name>Pavel</name>
            <isAnonymous/>
            <username>zencd</username>
        </author>
        <ipAddress>188.134.44.209</ipAddress>
        <isClosed/>
        <isDeleted/>
    </thread>
    <thread dsq:id="678832935">
        <id/>
        <forum>sovietraregroove</forum>
        <category dsq:id="734737"/>
        <link>http://3.sovietraregroove.appspot.com/the-soul-surfers</link>
        <title>- Soviet Rare Groove - Soviet Groove</title>
        <message/>
        <createdAt>2012-05-07T02:24:36Z</createdAt>
        <author>
            <email>zeencd@gmail.com</email>
            <name>Pavel</name>
            <isAnonymous/>
            <username>zencd</username>
        </author>
        <ipAddress>188.134.90.72</ipAddress>
        <isClosed/>
        <isDeleted/>
    </thread>
    <thread dsq:id="678917064">
        <id/>
        <forum>sovietraregroove</forum>
        <category dsq:id="734737"/>
        <link>http://3.sovietraregroove.appspot.com/q-tipokratiya</link>
        <title>- Soviet Rare Groove - Soviet Groove</title>
        <message/>
        <createdAt>2012-05-07T03:49:36Z</createdAt>
        <author>
            <email>zeencd@gmail.com</email>
            <name>Pavel</name>
            <isAnonymous/>
            <username>zencd</username>
        </author>
        <ipAddress>188.134.90.72</ipAddress>
        <isClosed/>
        <isDeleted/>
    </thread>
    <thread dsq:id="678917702">
        <id/>
        <forum>sovietraregroove</forum>
        <category dsq:id="734737"/>
        <link>http://3.sovietraregroove.appspot.com/one-year-of-the-blog</link>
        <title>- Soviet Rare Groove - Soviet Groove</title>
        <message/>
        <createdAt>2012-05-07T03:50:10Z</createdAt>
        <author>
            <email>zeencd@gmail.com</email>
            <name>Pavel</name>
            <isAnonymous/>
            <username>zencd</username>
        </author>
        <ipAddress>188.134.90.72</ipAddress>
        <isClosed/>
        <isDeleted/>
    </thread>
    <thread dsq:id="678919407">
        <id/>
        <forum>sovietraregroove</forum>
        <category dsq:id="734737"/>
        <link>http://3.sovietraregroove.appspot.com/dielo-1972</link>
        <title>- Soviet Rare Groove - Soviet Groove</title>
        <message/>
        <createdAt>2012-05-07T03:51:56Z</createdAt>
        <author>
            <email>zeencd@gmail.com</email>
            <name>Pavel</name>
            <isAnonymous/>
            <username>zencd</username>
        </author>
        <ipAddress>188.134.90.72</ipAddress>
        <isClosed/>
        <isDeleted/>
    </thread>
    <thread dsq:id="678920608">
        <id/>
        <forum>sovietraregroove</forum>
        <category dsq:id="734737"/>
        <link>http://3.sovietraregroove.appspot.com/dj-elns-soviet-grooves-mix-sovok</link>
        <title>- Soviet Rare Groove - Soviet Groove</title>
        <message/>
        <createdAt>2012-05-07T03:53:03Z</createdAt>
        <author>
            <email>zeencd@gmail.com</email>
            <name>Pavel</name>
            <isAnonymous/>
            <username>zencd</username>
        </author>
        <ipAddress>188.134.90.72</ipAddress>
        <isClosed/>
        <isDeleted/>
    </thread>
    <thread dsq:id="679469913">
        <id/>
        <forum>sovietraregroove</forum>
        <category dsq:id="734737"/>
        <link>http://3.sovietraregroove.appspot.com/</link>
        <title>Soviet Rare Groove - Soviet Groove</title>
        <message/>
        <createdAt>2012-05-07T12:47:26Z</createdAt>
        <author>
            <email>zeencd@gmail.com</email>
            <name>Pavel</name>
            <isAnonymous/>
            <username>zencd</username>
        </author>
        <ipAddress>188.134.90.72</ipAddress>
        <isClosed/>
        <isDeleted/>
    </thread>
    <thread dsq:id="679774606">
        <id/>
        <forum>sovietraregroove</forum>
        <category dsq:id="734737"/>
        <link>http://sovietraregroove.appspot.com/the-soul-surfers</link>
        <title>- Soviet Rare Groove - Soviet Groove</title>
        <message/>
        <createdAt>2012-05-07T17:43:21Z</createdAt>
        <author>
            <email>zeencd@gmail.com</email>
            <name>Pavel</name>
            <isAnonymous/>
            <username>zencd</username>
        </author>
        <ipAddress>188.134.90.72</ipAddress>
        <isClosed/>
        <isDeleted/>
    </thread>
    <thread dsq:id="680148260">
        <id/>
        <forum>sovietraregroove</forum>
        <category dsq:id="734737"/>
        <link>http://3.sovietraregroove.appspot.com/muslim-magomayev-my-city-baku-1973</link>
        <title>- Soviet Rare Groove - Soviet Groove</title>
        <message/>
        <createdAt>2012-05-08T00:06:35Z</createdAt>
        <author>
            <email>zeencd@gmail.com</email>
            <name>Pavel</name>
            <isAnonymous/>
            <username>zencd</username>
        </author>
        <ipAddress>188.134.90.72</ipAddress>
        <isClosed/>
        <isDeleted/>
    </thread>
    <thread dsq:id="680149649">
        <id/>
        <forum>sovietraregroove</forum>
        <category dsq:id="734737"/>
        <link>http://3.sovietraregroove.appspot.com/retro-video-ad-of-a-mixing-console</link>
        <title>- Soviet Rare Groove - Soviet Groove</title>
        <message/>
        <createdAt>2012-05-08T00:08:07Z</createdAt>
        <author>
            <email>zeencd@gmail.com</email>
            <name>Pavel</name>
            <isAnonymous/>
            <username>zencd</username>
        </author>
        <ipAddress>188.134.90.72</ipAddress>
        <isClosed/>
        <isDeleted/>
    </thread>
    <thread dsq:id="680150659">
        <id/>
        <forum>sovietraregroove</forum>
        <category dsq:id="734737"/>
        <link>http://3.sovietraregroove.appspot.com/the-disco-group-vs-john-davis</link>
        <title>- Soviet Rare Groove - Soviet Groove</title>
        <message/>
        <createdAt>2012-05-08T00:09:18Z</createdAt>
        <author>
            <email>zeencd@gmail.com</email>
            <name>Pavel</name>
            <isAnonymous/>
            <username>zencd</username>
        </author>
        <ipAddress>188.134.90.72</ipAddress>
        <isClosed/>
        <isDeleted/>
    </thread>
    <thread dsq:id="680150863">
        <id/>
        <forum>sovietraregroove</forum>
        <category dsq:id="734737"/>
        <link>http://3.sovietraregroove.appspot.com/disco-vs-hudson-county</link>
        <title>- Soviet Rare Groove - Soviet Groove</title>
        <message/>
        <createdAt>2012-05-08T00:09:32Z</createdAt>
        <author>
            <email>zeencd@gmail.com</email>
            <name>Pavel</name>
            <isAnonymous/>
            <username>zencd</username>
        </author>
        <ipAddress>188.134.90.72</ipAddress>
        <isClosed/>
        <isDeleted/>
    </thread>
    <thread dsq:id="680193907">
        <id/>
        <forum>sovietraregroove</forum>
        <category dsq:id="734737"/>
        <link>http://3.sovietraregroove.appspot.com/konstantin-orbelian-and-armenian-state-orchestra-1974</link>
        <title>- Soviet Rare Groove - Soviet Groove</title>
        <message/>
        <createdAt>2012-05-08T01:01:53Z</createdAt>
        <author>
            <email>zeencd@gmail.com</email>
            <name>Pavel</name>
            <isAnonymous/>
            <username>zencd</username>
        </author>
        <ipAddress>188.134.90.72</ipAddress>
        <isClosed/>
        <isDeleted/>
    </thread>
    <thread dsq:id="680195392">
        <id/>
        <forum>sovietraregroove</forum>
        <category dsq:id="734737"/>
        <link>http://3.sovietraregroove.appspot.com/konstantin-orbelian-dilizhan</link>
        <title>- Soviet Rare Groove - Soviet Groove</title>
        <message/>
        <createdAt>2012-05-08T01:03:30Z</createdAt>
        <author>
            <email>zeencd@gmail.com</email>
            <name>Pavel</name>
            <isAnonymous/>
            <username>zencd</username>
        </author>
        <ipAddress>188.134.90.72</ipAddress>
        <isClosed/>
        <isDeleted/>
    </thread>
    <thread dsq:id="680197736">
        <id/>
        <forum>sovietraregroove</forum>
        <category dsq:id="734737"/>
        <link>http://3.sovietraregroove.appspot.com/soviet-electro-mixtype</link>
        <title>- Soviet Rare Groove - Soviet Groove</title>
        <message/>
        <createdAt>2012-05-08T01:06:18Z</createdAt>
        <author>
            <email>zeencd@gmail.com</email>
            <name>Pavel</name>
            <isAnonymous/>
            <username>zencd</username>
        </author>
        <ipAddress>188.134.90.72</ipAddress>
        <isClosed/>
        <isDeleted/>
    </thread>
    <post dsq:id="170715182">
        <id/>
        <message><![CDATA[<p>test</p>]]></message>
        <createdAt>2011-03-24T04:02:26Z</createdAt>
        <author>
            <email>zeencd@gmail.com</email>
            <name>Pavel</name>
            <isAnonymous>true</isAnonymous>
            <username>zencd</username>
        </author>
        <ipAddress>188.134.44.209</ipAddress>
        <thread dsq:id="261688000"/>
    </post>
    <post dsq:id="521329636">
        <id/>
        <message>
            <![CDATA[<p>Later The Soul Surfers from city of Nizhny Novgorod was estabilished by DJ ELN (who also has recorded one of two most impressive soviet groove mixes ever made). The band has many aliases like Snow Surfers, United Boppers Unit, Gospel Surfers and Rhythm Cowboys. They have several 7" released already and here is their fresh Funk Night Records’ one.</p>]]></message>
        <createdAt>2012-05-07T02:40:02Z</createdAt>
        <author>
            <email>zeencd@gmail.com</email>
            <name>Pavel</name>
            <isAnonymous>true</isAnonymous>
            <username>zencd</username>
        </author>
        <ipAddress>188.134.90.72</ipAddress>
        <thread dsq:id="678832935"/>
    </post>
    <post dsq:id="521330047">
        <id/>
        <message><![CDATA[<p>Замечательный нижегородский дип-фанк бэнд</p>]]></message>
        <createdAt>2012-05-07T02:41:03Z</createdAt>
        <author>
            <email>zeencd@gmail.com</email>
            <name>Pavel</name>
            <isAnonymous>true</isAnonymous>
            <username>zencd</username>
        </author>
        <ipAddress>188.134.90.72</ipAddress>
        <thread dsq:id="678832935"/>
        <parent dsq:id="521329636"/>
    </post>
    <post dsq:id="522096189">
        <id/>
        <message><![CDATA[<p>test</p>]]></message>
        <createdAt>2012-05-08T00:11:38Z</createdAt>
        <author>
            <email>zeencd@gmail.com</email>
            <name>Pavel</name>
            <isAnonymous>true</isAnonymous>
            <username>zencd</username>
        </author>
        <ipAddress>188.134.90.72</ipAddress>
        <thread dsq:id="678920608"/>
    </post>
    <post dsq:id="522165199">
        <id/>
        <message><![CDATA[<p>nnn</p>]]></message>
        <createdAt>2012-05-08T00:53:13Z</createdAt>
        <author>
            <email/>
            <name>Pavel Vlasov</name>
            <isAnonymous>true</isAnonymous>
            <username>facebook-791939641</username>
        </author>
        <ipAddress>188.134.90.72</ipAddress>
        <thread dsq:id="678832935"/>
    </post>
</disqus>
